nezzle/VERSION
nezzle/__init__.py
nezzle/app.py
nezzle/constants.py
nezzle/convert.py
nezzle/mainwindow.py
nezzle/menu.py
nezzle/systemstate.py
nezzle/adjustment/__init__.py
nezzle/adjustment/label.py
nezzle/dialogs/__init__.py
nezzle/dialogs/exportimagedialog.py
nezzle/dialogs/opennetworkdialog.py
nezzle/dialogs/progressdialog.py
nezzle/graphics/__init__.py
nezzle/graphics/attributemapper.py
nezzle/graphics/baseitem.py
nezzle/graphics/mixins.py
nezzle/graphics/network.py
nezzle/graphics/quadbezier.py
nezzle/graphics/screen.py
nezzle/graphics/arrows/__init__.py
nezzle/graphics/arrows/arrowclassfactory.py
nezzle/graphics/arrows/basearrow.py
nezzle/graphics/arrows/transform.py
nezzle/graphics/edges/__init__.py
nezzle/graphics/edges/baseedge.py
nezzle/graphics/edges/controlpoint.py
nezzle/graphics/edges/curvededge.py
nezzle/graphics/edges/edgeconverter.py
nezzle/graphics/edges/edgefactory.py
nezzle/graphics/edges/elbowedge.py
nezzle/graphics/edges/selfloopedge.py
nezzle/graphics/edges/straightedge.py
nezzle/graphics/labels/__init__.py
nezzle/graphics/labels/labelfactory.py
nezzle/graphics/labels/textlabel.py
nezzle/graphics/nodes/__init__.py
nezzle/graphics/nodes/basenode.py
nezzle/graphics/nodes/ellipsenode.py
nezzle/graphics/nodes/nodeconverter.py
nezzle/graphics/nodes/nodefactory.py
nezzle/graphics/nodes/rectanglenode.py
nezzle/history/__init__.py
nezzle/history/commands.py
nezzle/history/history.py
nezzle/io/__init__.py
nezzle/io/cytoscape.py
nezzle/io/gexf.py
nezzle/io/image.py
nezzle/io/nzj.py
nezzle/io/sif.py
nezzle/managers/__init__.py
nezzle/managers/codemanager.py
nezzle/managers/consoletabmanager.py
nezzle/managers/historyviewmanager.py
nezzle/managers/networkmodelmanager.py
nezzle/managers/networktreemanager.py
nezzle/managers/singleviewmanager.py
nezzle/resources/__init__.py
nezzle/resources/icon.png
nezzle/resources/logo.png
nezzle/tests/__init__.py
nezzle/tests/jkwon_egfr_pathway.sif
nezzle/tests/korkut_2015.json
nezzle/tests/test_copy_graphics_items.py
nezzle-0.1.2.dist-info/LICENSE
nezzle-0.1.2.dist-info/METADATA
nezzle-0.1.2.dist-info/WHEEL
nezzle-0.1.2.dist-info/entry_points.txt
nezzle-0.1.2.dist-info/top_level.txt
nezzle-0.1.2.dist-info/RECORD
