Metadata-Version: 2.1
Name: nezzle
Version: 0.1.2
Summary: Nezzle: a programmable and interactive network visualization software
Home-page: https://github.com/dwgoon/nezzle
Author: Daewon Lee
Author-email: daewon4you@gmail.com
License: MIT
Classifier: License :: OSI Approved :: MIT License
Classifier: Operating System :: MacOS
Classifier: Operating System :: Microsoft :: Windows
Classifier: Operating System :: POSIX :: Linux
Classifier: Programming Language :: Python :: 3
Classifier: Programming Language :: Python :: 3.6
Classifier: Programming Language :: Python :: 3.7
Classifier: Programming Language :: Python :: 3.8
Classifier: Programming Language :: Python :: 3.9
Requires-Python: >=3.6
License-File: LICENSE
